iopath/__init__.py
iopath/version.py
iopath/common/__init__.py
iopath/common/download.py
iopath/common/file_io.py
iopath/common/non_blocking_io.py
iopath/tabular/__init__.py
iopath/tabular/tabular_io.py
iopath-0.1.8.dist-info/LICENSE
iopath-0.1.8.dist-info/METADATA
iopath-0.1.8.dist-info/WHEEL
iopath-0.1.8.dist-info/top_level.txt
iopath-0.1.8.dist-info/RECORD
