Metadata-Version: 2.1
Name: iopath
Version: 0.1.8
Summary: A library for providing I/O abstraction.
Home-page: https://github.com/facebookresearch/iopath
Author: FAIR
License: MIT licensed, as found in the LICENSE file
Platform: UNKNOWN
Requires-Python: >=3.6
Requires-Dist: tqdm
Requires-Dist: portalocker
Requires-Dist: dataclasses ; python_version < "3.7"
